odoo8_addon_account_credit_control_dunning_fees-8.0.0.1.0.99.dev39-py3.8-nspkg.pth
odoo_addons/account_credit_control_dunning_fees/README.rst
odoo_addons/account_credit_control_dunning_fees/__init__.py
odoo_addons/account_credit_control_dunning_fees/__openerp__.py
odoo_addons/account_credit_control_dunning_fees/i18n/account_credit_control_dunning_fees.pot
odoo_addons/account_credit_control_dunning_fees/i18n/am.po
odoo_addons/account_credit_control_dunning_fees/i18n/ar.po
odoo_addons/account_credit_control_dunning_fees/i18n/bg.po
odoo_addons/account_credit_control_dunning_fees/i18n/bs.po
odoo_addons/account_credit_control_dunning_fees/i18n/ca.po
odoo_addons/account_credit_control_dunning_fees/i18n/ca_ES.po
odoo_addons/account_credit_control_dunning_fees/i18n/cs.po
odoo_addons/account_credit_control_dunning_fees/i18n/da.po
odoo_addons/account_credit_control_dunning_fees/i18n/de.po
odoo_addons/account_credit_control_dunning_fees/i18n/el_GR.po
odoo_addons/account_credit_control_dunning_fees/i18n/en_GB.po
odoo_addons/account_credit_control_dunning_fees/i18n/es.po
odoo_addons/account_credit_control_dunning_fees/i18n/es_AR.po
odoo_addons/account_credit_control_dunning_fees/i18n/es_CL.po
odoo_addons/account_credit_control_dunning_fees/i18n/es_CO.po
odoo_addons/account_credit_control_dunning_fees/i18n/es_CR.po
odoo_addons/account_credit_control_dunning_fees/i18n/es_DO.po
odoo_addons/account_credit_control_dunning_fees/i18n/es_EC.po
odoo_addons/account_credit_control_dunning_fees/i18n/es_ES.po
odoo_addons/account_credit_control_dunning_fees/i18n/es_MX.po
odoo_addons/account_credit_control_dunning_fees/i18n/es_PE.po
odoo_addons/account_credit_control_dunning_fees/i18n/es_PY.po
odoo_addons/account_credit_control_dunning_fees/i18n/es_VE.po
odoo_addons/account_credit_control_dunning_fees/i18n/et.po
odoo_addons/account_credit_control_dunning_fees/i18n/eu.po
odoo_addons/account_credit_control_dunning_fees/i18n/fa.po
odoo_addons/account_credit_control_dunning_fees/i18n/fi.po
odoo8_addon_account_credit_control_dunning_fees-8.0.0.1.0.99.dev39.dist-info/METADATA
odoo8_addon_account_credit_control_dunning_fees-8.0.0.1.0.99.dev39.dist-info/WHEEL
odoo8_addon_account_credit_control_dunning_fees-8.0.0.1.0.99.dev39.dist-info/namespace_packages.txt
odoo8_addon_account_credit_control_dunning_fees-8.0.0.1.0.99.dev39.dist-info/top_level.txt
odoo8_addon_account_credit_control_dunning_fees-8.0.0.1.0.99.dev39.dist-info/RECORD
